{
  "placeholderImages": [
    { "id": "sticker-1", "description": "Promo & CTA", "imageUrl": "https://picsum.photos/seed/sticker1/400/400", "imageHint": "sticker design" },
    { "id": "sticker-2", "description": "Perguntas", "imageUrl": "https://picsum.photos/seed/sticker2/400/400", "imageHint": "sticker design" },
    { "id": "sticker-3", "description": "Bastidores", "imageUrl": "https://picsum.photos/seed/sticker3/400/400", "imageHint": "sticker design" },
    { "id": "sticker-4", "description": "Motivação", "imageUrl": "https://picsum.photos/seed/sticker4/400/400", "imageHint": "sticker design" },
    { "id": "sticker-5", "description": "Enquetes", "imageUrl": "https://picsum.photos/seed/sticker5/400/400", "imageHint": "sticker design" },
    { "id": "sticker-6", "description": "Lembretes", "imageUrl": "https://picsum.photos/seed/sticker6/400/400", "imageHint": "sticker design" },
    { "id": "sticker-7", "description": "Reações", "imageUrl": "https://picsum.photos/seed/sticker7/400/400", "imageHint": "sticker design" },
    { "id": "sticker-8", "description": "Vendas", "imageUrl": "https://picsum.photos/seed/sticker8/400/400", "imageHint": "sticker design" },
    { "id": "social-1", "description": "Depoimento de cliente 1", "imageUrl": "https://i.imgur.com/anNiOMY.jpeg", "imageHint": "testimonial screenshot" },
    { "id": "social-2", "description": "Depoimento de cliente 2", "imageUrl": "https://i.imgur.com/oqLgnj3.jpeg", "imageHint": "testimonial screenshot" },
    { "id": "social-3", "description": "Depoimento de cliente 3", "imageUrl": "https://i.imgur.com/dPufIUU.jpeg", "imageHint": "testimonial screenshot" },
    { "id": "social-4", "description": "Depoimento de cliente 4", "imageUrl": "https://i.imgur.com/tG8d9mH.jpeg", "imageHint": "testimonial screenshot" },
    { "id": "social-5", "description": "Depoimento de cliente 5", "imageUrl": "https://i.imgur.com/ouWdw3B.jpeg", "imageHint": "testimonial screenshot" }
  ]
}
